cibc_sftp_server/__init__.py
cibc_sftp_server/download_files.py
cibc_sftp_server/manipulate_reports.py
cibc_sftp_server/sftp_connection.py
cibc_sftp_server/upload_files.py
access_sftp_server-0.1.0.dist-info/LICENSE.txt
access_sftp_server-0.1.0.dist-info/METADATA
access_sftp_server-0.1.0.dist-info/WHEEL
access_sftp_server-0.1.0.dist-info/top_level.txt
access_sftp_server-0.1.0.dist-info/RECORD
