Metadata-Version: 2.1
Name: access-sftp-server
Version: 0.1.0
Summary: Access SFTP Server
Home-page: UNKNOWN
Author: Valentin Baier
Author-email: valentin_baier@gmx.de
License: UNKNOWN
Keywords: python,sftp,server,cibc,upload_files,download_files
Platform: UNKNOWN
Classifier: Development Status :: 1 - Planning
Classifier: Intended Audience :: Developers
Classifier: Programming Language :: Python :: 3
Classifier: Operating System :: Unix
Classifier: Operating System :: MacOS :: MacOS X
Classifier: Operating System :: Microsoft :: Windows
License-File: LICENSE.txt
Requires-Dist: paramiko
Requires-Dist: openpyxl
Requires-Dist: gspread
Requires-Dist: pandas
